JavaXiangmuDaquanChuyiFix1/README.md
JavaXiangmuDaquanChuyiFix1/__init__.py
JavaXiangmuDaquanChuyiFix1/__main__.py
JavaXiangmuDaquanChuyiFix1/file.epub
JavaXiangmuDaquanChuyiFix1/index.html
JavaXiangmuDaquanChuyiFix1/css/__init__.py
JavaXiangmuDaquanChuyiFix1/css/annotations.css
JavaXiangmuDaquanChuyiFix1/css/main.css
JavaXiangmuDaquanChuyiFix1/css/normalize.css
JavaXiangmuDaquanChuyiFix1/css/popup.css
JavaXiangmuDaquanChuyiFix1/font/__init__.py
JavaXiangmuDaquanChuyiFix1/font/fontello.eot
JavaXiangmuDaquanChuyiFix1/font/fontello.svg
JavaXiangmuDaquanChuyiFix1/font/fontello.ttf
JavaXiangmuDaquanChuyiFix1/font/fontello.woff
JavaXiangmuDaquanChuyiFix1/img/__init__.py
JavaXiangmuDaquanChuyiFix1/img/annotator-glyph-sprite.png
JavaXiangmuDaquanChuyiFix1/img/annotator-icon-sprite.png
JavaXiangmuDaquanChuyiFix1/img/apple-touch-icon.png
JavaXiangmuDaquanChuyiFix1/img/cancelfullscreen.png
JavaXiangmuDaquanChuyiFix1/img/close.png
JavaXiangmuDaquanChuyiFix1/img/fullscreen.png
JavaXiangmuDaquanChuyiFix1/img/loader.gif
JavaXiangmuDaquanChuyiFix1/img/menu-icon.png
JavaXiangmuDaquanChuyiFix1/img/save.png
JavaXiangmuDaquanChuyiFix1/img/saved.png
JavaXiangmuDaquanChuyiFix1/img/settings-s.png
JavaXiangmuDaquanChuyiFix1/img/settings.png
JavaXiangmuDaquanChuyiFix1/img/star.png
JavaXiangmuDaquanChuyiFix1/js/__init__.py
JavaXiangmuDaquanChuyiFix1/js/epub.js
JavaXiangmuDaquanChuyiFix1/js/epub.min.js
JavaXiangmuDaquanChuyiFix1/js/epub.min.map
JavaXiangmuDaquanChuyiFix1/js/hooks.min.js
JavaXiangmuDaquanChuyiFix1/js/hooks.min.map
JavaXiangmuDaquanChuyiFix1/js/reader.js
JavaXiangmuDaquanChuyiFix1/js/reader.js.map
JavaXiangmuDaquanChuyiFix1/js/reader.min.js
JavaXiangmuDaquanChuyiFix1/js/reader.min.map
JavaXiangmuDaquanChuyiFix1/js/hooks/__init__.py
JavaXiangmuDaquanChuyiFix1/js/hooks/extensions/__init__.py
JavaXiangmuDaquanChuyiFix1/js/hooks/extensions/highlight.js
JavaXiangmuDaquanChuyiFix1/js/libs/__init__.py
JavaXiangmuDaquanChuyiFix1/js/libs/jquery.min.js
java_xiangmu_daquan_chuyi_fix1-2025.3.25.0.dist-info/METADATA
java_xiangmu_daquan_chuyi_fix1-2025.3.25.0.dist-info/WHEEL
java_xiangmu_daquan_chuyi_fix1-2025.3.25.0.dist-info/entry_points.txt
java_xiangmu_daquan_chuyi_fix1-2025.3.25.0.dist-info/top_level.txt
java_xiangmu_daquan_chuyi_fix1-2025.3.25.0.dist-info/RECORD
